LICENSE
MANIFEST.in
README.md
setup.cfg
setup.py
djeasy/__init__.py
djeasy.egg-info/PKG-INFO
djeasy.egg-info/SOURCES.txt
djeasy.egg-info/dependency_links.txt
djeasy.egg-info/entry_points.txt
djeasy.egg-info/not-zip-safe
djeasy.egg-info/requires.txt
djeasy.egg-info/top_level.txt
djeasy/client/__init__.py
djeasy/client/management.py
djeasy/client/file/gunicorn.service
djeasy/client/file/nginx
djeasy/client/file/package.json
djeasy/client/file/server.info
djeasy/package/__init__.py